pnap_location_api/__init__.py
pnap_location_api/api_client.py
pnap_location_api/api_response.py
pnap_location_api/configuration.py
pnap_location_api/exceptions.py
pnap_location_api/py.typed
pnap_location_api/rest.py
pnap_location_api/version.py
pnap_location_api/api/__init__.py
pnap_location_api/api/locations_api.py
pnap_location_api/models/__init__.py
pnap_location_api/models/error.py
pnap_location_api/models/location.py
pnap_location_api/models/location_enum.py
pnap_location_api/models/product_category.py
pnap_location_api/models/product_category_enum.py
pnap_location_api-2.0.4.dist-info/METADATA
pnap_location_api-2.0.4.dist-info/WHEEL
pnap_location_api-2.0.4.dist-info/top_level.txt
pnap_location_api-2.0.4.dist-info/RECORD
